pysvn/LICENSE.txt
pysvn/__init__.py
pysvn/_pysvn_3_9.pyd
pysvn/apr_crypto_openssl-1.dll
pysvn/apr_dbd_odbc-1.dll
pysvn/apr_ldap-1.dll
pysvn/expat.dll
pysvn/libapr-1.dll
pysvn/libapriconv-1.dll
pysvn/libaprutil-1.dll
pysvn/libcrypto-1_1-x64.dll
pysvn/libeay32.dll
pysvn/libserf-1.dll
pysvn/libssl-1_1-x64.dll
pysvn/libsvn_client-1.dll
pysvn/libsvn_delta-1.dll
pysvn/libsvn_diff-1.dll
pysvn/libsvn_fs-1.dll
pysvn/libsvn_fs_fs-1.dll
pysvn/libsvn_fs_util-1.dll
pysvn/libsvn_fs_x-1.dll
pysvn/libsvn_ra-1.dll
pysvn/libsvn_repos-1.dll
pysvn/libsvn_subr-1.dll
pysvn/libsvn_wc-1.dll
pysvn/pysvn.html
pysvn/pysvn_prog_guide.html
pysvn/pysvn_prog_ref.html
pysvn/pysvn_prog_ref.js
pysvn/ssleay32.dll
pysvn/zlib1.dll
pysvn/Examples/Client/parse_datetime.py
pysvn/Examples/Client/svn_cmd.py
pysvn_wheel-1.9.13.dist-info/LICENSE
pysvn_wheel-1.9.13.dist-info/METADATA
pysvn_wheel-1.9.13.dist-info/WHEEL
pysvn_wheel-1.9.13.dist-info/top_level.txt
pysvn_wheel-1.9.13.dist-info/RECORD
