Metadata-Version: 2.1
Name: pysvn-wheel
Version: 1.9.13
Summary: Subversion support for Python
Home-page: https://pysvn.sourceforge.io/
Author: Mellkori
Author-email: milos.slavik@outlook.com
License: MIT
Keywords: subversion
Platform: win32
Classifier: Development Status :: 5 - Production/Stable
Classifier: Intended Audience :: Developers
Classifier: Topic :: Software Development :: Version Control
Classifier: Environment :: Win32 (MS Windows)
Classifier: Operating System :: Microsoft :: Windows
License-File: LICENSE
